service_sms/__init__.py
service_sms/setup.py
service_sms/sms_service.py
service_sms/utils.py
service_sms/whatsapp_service.py
service_sms-0.1.0.dist-info/METADATA
service_sms-0.1.0.dist-info/WHEEL
service_sms-0.1.0.dist-info/top_level.txt
service_sms-0.1.0.dist-info/RECORD
